setup.py
opencrack/__init__.py
opencrack/exceptions.py
opencrack/models.py
opencrack/utils.py
opencrack.egg-info/PKG-INFO
opencrack.egg-info/SOURCES.txt
opencrack.egg-info/dependency_links.txt
opencrack.egg-info/not-zip-safe
opencrack.egg-info/top_level.txt