Metadata-Version: 1.1
Name: opencrack
Version: 0.0.1
Summary: Python interface to generically interact with OpenStack APIs
Home-page: https://github.com/CloudA/opencrack
Author: Cloud-A Computing Inc.
Author-email: info@clouda.ca
License: BSD
Platform: any
Classifier: Development Status :: 3 - Alpha
Classifier: Environment :: Console
Classifier: Intended Audience :: Developers
Classifier: License :: OSI Approved :: BSD License
Classifier: Operating System :: POSIX
Classifier: Operating System :: MacOS
Classifier: Operating System :: Unix
Classifier: Programming Language :: Python
Classifier: Programming Language :: Python :: 2
Classifier: Programming Language :: Python :: 3
Classifier: Topic :: Software Development :: Libraries :: Python Modules
